README.md
conftest.py
setup.cfg
setup.py
morjus_kinopoisk_tests.egg-info/PKG-INFO
morjus_kinopoisk_tests.egg-info/SOURCES.txt
morjus_kinopoisk_tests.egg-info/dependency_links.txt
morjus_kinopoisk_tests.egg-info/not-zip-safe
morjus_kinopoisk_tests.egg-info/requires.txt
morjus_kinopoisk_tests.egg-info/top_level.txt
pages/base_page.py
pages/hd_page.py
pages/hd_profiles_page.py
pages/header_page.py
pages/main_page.py
pages/media_page.py
pages/movie_page.py
pages/recommendation_page.py
pages/search_page.py
pages/user_page.py
tests/test_kinoposk.py