Metadata-Version: 1.2
Name: morjus-kinopoisk-tests
Version: 0.1
Summary: Package for kinopoisk tests
Home-page: https://github.com/Morjus/kinopoisk_ui_tests
Author: Morjus
Author-email: morjus@yandex.ru
License: MIT
Keywords: KINOPOISK,UI_TESTS
Platform: linux
Classifier: Development Status :: 3 - Alpha
Classifier: Intended Audience :: Developers
Classifier: Topic :: Software Development :: Build Tools
Classifier: License :: OSI Approved :: MIT License
Classifier: Programming Language :: Python :: 3
Classifier: Programming Language :: Python :: 3.4
Classifier: Programming Language :: Python :: 3.5
Classifier: Programming Language :: Python :: 3.6
Requires-Python: >3.6
